setup.cfg
setup.py
bazaarrecipe/__init__.py
bazaarrecipe.egg-info/PKG-INFO
bazaarrecipe.egg-info/SOURCES.txt
bazaarrecipe.egg-info/dependency_links.txt
bazaarrecipe.egg-info/entry_points.txt
bazaarrecipe.egg-info/not-zip-safe
bazaarrecipe.egg-info/top_level.txt
