Metadata-Version: 1.0
Name: bazaarrecipe
Version: 0.1dev
Summary: Buildout recipe for Bazaar
Home-page: https://launchpad.net/bazaarrecipe
Author: Jeroen Vloothuis
Author-email: jeroen.vloothuis@xs4all.nl
License: GPL
Platform: UNKNOWN
Classifier: Framework :: Buildout
Classifier: Topic :: Software Development :: Build Tools
Classifier: Development Status :: 3 - Alpha
Classifier: License :: OSI Approved :: BSD License
